README.rst
djhacker.py
setup.py
djhacker.egg-info/PKG-INFO
djhacker.egg-info/SOURCES.txt
djhacker.egg-info/dependency_links.txt
djhacker.egg-info/requires.txt
djhacker.egg-info/top_level.txt