Metadata-Version: 2.1
Name: djhacker
Version: 0.1.2
Summary: Django-Hacker: customize default django forms
Home-page: https://yourlabs.io/oss/django-djhacker
Author: James Pic
Author-email: jamespic@gmail.com
License: MIT
Keywords: django forms
Platform: UNKNOWN
Requires-Python: >=3.7
Provides-Extra: test
